MANIFEST.in
README.md
requirements-dev.txt
requirements.txt
setup.cfg
setup.py
fly_jwt/__init__.py
fly_jwt/config.py
fly_jwt/helper.py
fly_jwt/jwt.py
fly_jwt.egg-info/PKG-INFO
fly_jwt.egg-info/SOURCES.txt
fly_jwt.egg-info/dependency_links.txt
fly_jwt.egg-info/not-zip-safe
fly_jwt.egg-info/requires.txt
fly_jwt.egg-info/top_level.txt