Metadata-Version: 2.1
Name: fly-jwt
Version: 0.2.0
Summary: JWT library for fly
Home-page: https://github.com/tatsuya4649/fly_jwt
Author: tatsuya.s
License: MIT
Keywords: fly,jwt,security
Platform: UNKNOWN
Classifier: Environment :: Web Environment
Classifier: License :: OSI Approved :: MIT License
Classifier: Programming Language :: Python :: 3.6
Classifier: Programming Language :: Python :: 3.7
Classifier: Programming Language :: Python :: 3.8
Classifier: Programming Language :: Python :: 3.9
Classifier: Programming Language :: Python :: 3.10
Classifier: Topic :: Internet
Classifier: Topic :: Internet :: WWW/HTTP
Classifier: Topic :: Internet :: WWW/HTTP :: HTTP Servers
Classifier: Topic :: Security
Classifier: Topic :: System :: Networking
Requires-Python: >=3.6
Provides-Extra: develop
